wyvern/__init__.py
wyvern/api.py
wyvern/aws/__init__.py
wyvern/aws/kinesis.py
wyvern/cli/commands.py
wyvern/clients/__init__.py
wyvern/clients/snowflake.py
wyvern/components/__init__.py
wyvern/components/api_route_component.py
wyvern/components/business_logic/__init__.py
wyvern/components/business_logic/boosting_business_logic.py
wyvern/components/business_logic/business_logic.py
wyvern/components/business_logic/pinning_business_logic.py
wyvern/components/candidates/__init__.py
wyvern/components/candidates/candidate_logger.py
wyvern/components/component.py
wyvern/components/events/__init__.py
wyvern/components/events/events.py
wyvern/components/features/__init__.py
wyvern/components/features/feature_logger.py
wyvern/components/features/feature_retrieval_pipeline.py
wyvern/components/features/feature_store.py
wyvern/components/features/realtime_features_component.py
wyvern/components/helpers/__init__.py
wyvern/components/helpers/linear_algebra.py
wyvern/components/helpers/polars.py
wyvern/components/helpers/sorting.py
wyvern/components/impressions/__init__.py
wyvern/components/impressions/impression_logger.py
wyvern/components/index/__init__.py
wyvern/components/index/_index.py
wyvern/components/models/__init__.py
wyvern/components/models/model_chain_component.py
wyvern/components/models/model_component.py
wyvern/components/models/modelbit_component.py
wyvern/components/pagination/__init__.py
wyvern/components/pagination/pagination_component.py
wyvern/components/pagination/pagination_fields.py
wyvern/components/pipeline_component.py
wyvern/components/ranking_pipeline.py
wyvern/components/single_entity_pipeline.py
wyvern/config.py
wyvern/core/__init__.py
wyvern/core/compression.py
wyvern/core/http.py
wyvern/entities/__init__.py
wyvern/entities/candidate_entities.py
wyvern/entities/feature_entities.py
wyvern/entities/identifier.py
wyvern/entities/identifier_entities.py
wyvern/entities/index_entities.py
wyvern/entities/model_entities.py
wyvern/entities/request.py
wyvern_ai-0.0.30.dist-info/LICENSE
wyvern_ai-0.0.30.dist-info/METADATA
wyvern_ai-0.0.30.dist-info/WHEEL
wyvern_ai-0.0.30.dist-info/entry_points.txt
wyvern_ai-0.0.30.dist-info/RECORD
